pyexphys/__init__.py
pyexphys/anthropometry.py
pyexphys/balance.py
pyexphys/composition.py
pyexphys/convert.py
pyexphys/enums.py
pyexphys/flexibility.py
pyexphys/mets.py
pyexphys/strength.py
pyexphys/cardio/__init__.py
pyexphys/cardio/cardiac.py
pyexphys/cardio/energy.py
pyexphys/cardio/respiration.py
pyexphys/equations/__init__.py
pyexphys/equations/setup.py
pyexphys/equations/balance/__init__.py
pyexphys/equations/cardiovascular/__init__.py
pyexphys/equations/cardiovascular/models/__init__.py
pyexphys/equations/composition/__init__.py
pyexphys/equations/flexibility/__init__.py
pyexphys/equations/mets/__init__.py
pyexphys/equations/sport/__init__.py
pyexphys/equations/sport/running/__init__.py
pyexphys/equations/strength/__init__.py
pyexphys/model/__init__.py
pyexphys/model/aerobic.py
pyexphys/sport/__init__.py
pyexphys/sport/running/__init__.py
pyexphys/sport/running/adjustment.py
pyexphys/sport/running/grading.py
pyexphys/sport/running/jackdaniels.py
pyexphys-2.1.2.dist-info/LICENSE.txt
pyexphys-2.1.2.dist-info/METADATA
pyexphys-2.1.2.dist-info/WHEEL
pyexphys-2.1.2.dist-info/top_level.txt
pyexphys-2.1.2.dist-info/RECORD
